README.rst
setup.py
django_suggestions.egg-info/PKG-INFO
django_suggestions.egg-info/SOURCES.txt
django_suggestions.egg-info/dependency_links.txt
django_suggestions.egg-info/top_level.txt
djangosuggestions/__init__.py
djangosuggestions/fields.py
djangosuggestions/models.py
djangosuggestions/widgets.py