Metadata-Version: 1.1
Name: django-suggestions
Version: 0.2.0
Summary: A Django form widget that implements the HTML5 form list element
Home-page: https://bitbucket.org/tim_heap/django-suggestions
Author: Tim Heap
Author-email: tim@timheap.me
License: UNKNOWN
Platform: UNKNOWN
Classifier: Environment :: Web Environment
Classifier: Intended Audience :: Developers
Classifier: Operating System :: OS Independent
Classifier: Programming Language :: Python
Classifier: Framework :: Django
